prq.py
examples/__init__.py
examples/connection.py
examples/tasks.py
scripts/__init__.py
scripts/job.py
scripts/log.py
scripts/redis_interactor.py
scripts/rqgenload.py
scripts/rqinfo.py
scripts/rqworker.py
prq-0.0.21.dist-info/METADATA
prq-0.0.21.dist-info/WHEEL
prq-0.0.21.dist-info/entry_points.txt
prq-0.0.21.dist-info/top_level.txt
prq-0.0.21.dist-info/RECORD
